{"title":"Combined feed","url":"https://LIVESTREAM-KR.github.io/beyondlive/all.xml","elements":[{"title":"[공연안내] TAEMIN SOLO CONCERT : METAMORPH 온라인 티켓 오픈 공지 (Beyond LIVE ─ 공지사항)","contents":"2023. 11. 27","retrieved":1701094306751},{"title":"[안내] PayPal 게스트 체크아웃 서비스 종료 (Beyond LIVE ─ 공지사항)","contents":"2023. 11. 21","retrieved":1701094306752},{"title":"[공연안내] MMA2023 (멜론 뮤직 어워즈) 온라인 티켓 오픈 공지 (Beyond LIVE ─ 공지사항)","contents":"2023. 11. 20","retrieved":1701094306753},{"title":"[안내]THE BOYZ 2ND WORLD TOUR : ZENERATION - ENCORE 아티스트 불참 안내 (Beyond LIVE ─ 공지사항)","contents":"2023. 11. 17","retrieved":1701094306757},{"title":"[공연안내] 사쿠라자카46 “3rd YEAR ANNIVERSARY LIVE”온라인 티켓 오픈 공지 (Beyond LIVE ─ 공지사항)","contents":"2023. 11. 11","retrieved":1701094306757},{"title":"[공연안내] THE BOYZ 2ND WORLD TOUR : ZENERATION – ENCORE 온라인 티켓 오픈 공지 (Beyond LIVE ─ 공지사항)","contents":"2023. 11. 09","retrieved":1701094306757},{"title":"[안내] Ado Japan Tour 2023 \"MARS\" VOD 출시 안내 (Beyond LIVE ─ 공지사항)","contents":"2023. 10. 31","retrieved":1701094306758},{"title":"[완료] Beyond LIVE 결제 서비스 점검 안내 (Beyond LIVE ─ 공지사항)","contents":"2023. 11. 16","retrieved":1701094306758},{"title":"[공연안내] 2023 aespa FAN MEETING ＜MY DRAMA＞온라인 티켓 오픈 공지 (Beyond LIVE ─ 공지사항)","contents":"2023. 11. 06","retrieved":1701094306759},{"title":"[공연안내] SUPER JUNIOR 18TH ANNIVERSARY SPECIAL EVENT <1t’s 8lue> Re-Streaming ONLY 티켓 오픈 공지 (Beyond LIVE ─ 공지사항)","contents":"2023. 11. 06","retrieved":1701094306760},{"title":"[12/17] TAEMIN SOLO CONCERT : METAMORPH (Beyond LIVE ─ 공연)","contents":"태민","retrieved":1701094313901,"image":"https://static.beyondlive.com/contents/hCrKsQCGWrrLiaI7g17rdHuXTZ7AFa8K.jpg"},{"title":"[12/16] TAEMIN SOLO CONCERT : METAMORPH (Beyond LIVE ─ 공연)","contents":"태민","retrieved":1701094313906,"image":"https://static.beyondlive.com/contents/NomtpbD7TnRrcfikha8P6oPi6NeAR4zD.jpg"},{"title":"[DAY2] 사쿠라자카46 “3rd YEAR ANNIVERSARY LIVE” Re-Streaming (Beyond LIVE ─ 공연)","contents":"사쿠라자카46","retrieved":1701094313906,"image":"https://static.beyondlive.com/contents/RlpqpTqsDrGjjxkxQR1ZXqzdGwFpXrbK.jpg"},{"title":"[DAY1] 사쿠라자카46 “3rd YEAR ANNIVERSARY LIVE” Re-Streaming (Beyond LIVE ─ 공연)","contents":"사쿠라자카46","retrieved":1701094313907,"image":"https://static.beyondlive.com/contents/05qePApiopIcUufe1FhVKA2qiOSZLhKJ.jpg"},{"title":"NCT 127 3RD TOUR ‘NEO CITY : SEOUL - THE UNITY’ Re-Streaming (Beyond LIVE ─ 공연)","contents":"NCT 127","retrieved":1701094313908,"image":"https://static.beyondlive.com/contents/hvKOXHl419ixMNE19JlIDc7SFvoHoK7Q.jpg"},{"title":"THE BOYZ 2ND WORLD TOUR : ZENERATION - ENCORE (Beyond LIVE ─ 공연)","contents":"THE BOYZ","retrieved":1701094313908,"image":"https://static.beyondlive.com/contents/tJk1kLoSHAjYXnHwYUu0G3yBFEgI9irN.jpg"},{"title":"2023 aespa FAN MEETING ＜MY DRAMA＞ Re-Streaming (Beyond LIVE ─ 공연)","contents":"aespa","retrieved":1701094313908,"image":"https://static.beyondlive.com/contents/c29ccd292dec49b9995ee891d6602dbb.png"},{"title":"MMA2023 (멜론 뮤직 어워즈) (Beyond LIVE ─ 공연)","contents":"MMA2023","retrieved":1701094313908,"image":"https://static.beyondlive.com/contents/jf34KtPKnWlMGtw5u982Nrq6rWioxaQg.jpg"},{"title":"[DAY2] 사쿠라자카46 “3rd YEAR ANNIVERSARY LIVE” (Beyond LIVE ─ 공연)","contents":"사쿠라자카46","retrieved":1701094313909,"image":"https://static.beyondlive.com/contents/CUpP03ERG4KE12OGlyiXmuQazConipzS.jpg"},{"title":"NCT 127 3RD TOUR ‘NEO CITY : SEOUL - THE UNITY’ (Beyond LIVE ─ 공연)","contents":"NCT 127","retrieved":1701094313910,"image":"https://static.beyondlive.com/contents/Fb4KUhQ5kIRGSl0hDYai1FdEHdvr2Glq.jpg"},{"title":"[DAY1] 사쿠라자카46 “3rd YEAR ANNIVERSARY LIVE” (Beyond LIVE ─ 공연)","contents":"사쿠라자카46","retrieved":1701094313910,"image":"https://static.beyondlive.com/contents/LjKe4JHfPBnWLjP941nngBHocBrQyNrb.jpg"},{"title":"SUPER JUNIOR 18TH ANNIVERSARY SPECIAL EVENT <1t’s 8lue> Re-Streaming (Beyond LIVE ─ 공연)","contents":"SUPER JUNIOR","retrieved":1701094313911,"image":"https://static.beyondlive.com/contents/pjkTs0dQoUBX7etyd3ndY3ICe0cxx6cp.jpg"},{"title":"2023 TWICE FANMEETING 〈ONCE AGAIN〉 Re-Streaming (Beyond LIVE ─ 공연)","contents":"TWICE","retrieved":1701094313912,"image":"https://static.beyondlive.com/contents/68d47a5db8454e6ab3f2012db476bf9f.jpg"},{"title":"2023 aespa FAN MEETING ＜MY DRAMA＞ (Beyond LIVE ─ 공연)","contents":"aespa","retrieved":1701094313915,"image":"https://static.beyondlive.com/contents/22e7d951cb4944debc2e8a700fb396e3.png"},{"title":"NMIXX THE 1ST FAN CONCERT NMIXX CHANGE UP : MIXX UNIVERSITY Re-Streaming (Beyond LIVE ─ 공연)","contents":"NMIXX","retrieved":1701094313915,"image":"https://static.beyondlive.com/contents/3417872875f346c5bbe2f42890e5788f.jpg"},{"title":"YESUNG SOLO CONCERT – Unfading Sense Re-Streaming (Beyond LIVE ─ 공연)","contents":"예성","retrieved":1701094313926,"image":"https://static.beyondlive.com/contents/ac98cbfea7ae4d2ebbd87ce0eb61e6dd.jpg"},{"title":"SUPER JUNIOR 18TH ANNIVERSARY SPECIAL EVENT <1t’s 8lue> (Beyond LIVE ─ 공연)","contents":"SUPER JUNIOR","retrieved":1701094313927,"image":"https://static.beyondlive.com/contents/utfVzJUUipnW6KUKFoQSwQDPk4U3elrb.jpg"},{"title":"Eve Arena Tour 2023 「kororon」 (Beyond LIVE ─ 공연)","contents":"Eve","retrieved":1701094313928,"image":"https://static.beyondlive.com/contents/6db8468a43da4bc5ba8d21e8963868fc.jpg"},{"title":"Yuzuru Hanyu ICE STORY 2nd \"RE_PRAY\" TOUR (Beyond LIVE ─ 공연)","contents":"하뉴 유즈루","retrieved":1701094313929,"image":"https://static.beyondlive.com/contents/6c11a2233d6d4b0385428abea3dd654a.jpg"},{"title":"SMTOWN LIVE 2023 SMCU PALACE @JAKARTA with KB Bank Re-Streaming (Beyond LIVE ─ 공연)","contents":"SMTOWN","retrieved":1701094313930,"image":"https://static.beyondlive.com/contents/ef4aeead3c7c4a8884aa2c51804bee7e.jpg"},{"title":"[12/16] TAEMIN SOLO CONCERT : METAMORPH (Beyond LIVE ─ TOP)","contents":"2023. 12. 16. 17:00 (KST)","link":"https://beyondlive.com/contents/321","retrieved":1701054773464,"image":"https://static.beyondlive.com/contents/7HUK4lNGNfHsiwNnd4u87IHO7GxpHkyh.jpg"},{"title":"[12/17] TAEMIN SOLO CONCERT : METAMORPH (Beyond LIVE ─ TOP)","contents":"2023. 12. 17. 16:00 (KST)","link":"https://beyondlive.com/contents/323","retrieved":1701054773468,"image":"https://static.beyondlive.com/contents/9JHqWQOgTWBlll6474qpVIcVBPL82ka7.jpg"},{"title":"THE BOYZ 2ND WORLD TOUR : ZENERATION - ENCORE (Beyond LIVE ─ TOP)","contents":"2023. 12. 03. 16:00 (KST)","link":"https://beyondlive.com/contents/315","retrieved":1699499519037,"image":"https://static.beyondlive.com/contents/JJsIrcI69pA7hd6KKj00Woi2ae6oq5e5.jpg"},{"title":"2023 aespa FAN MEETING ＜MY DRAMA＞ Re-Streaming (Beyond LIVE ─ TOP)","contents":"2023. 12. 02. 20:00 (KST)","link":"https://beyondlive.com/contents/308","retrieved":1700230281465,"image":"https://static.beyondlive.com/contents/74c4e3e63c2c4add99ffe0006ef13d07.png"},{"title":"NCT 127 3RD TOUR ‘NEO CITY : SEOUL - THE UNITY’ Re-Streaming (Beyond LIVE ─ TOP)","contents":"2023. 12. 09. 18:00 (KST)","link":"https://beyondlive.com/contents/314","retrieved":1700997013556,"image":"https://static.beyondlive.com/contents/IjOC3kLtP7lfTMoPuxOM574imICjOjL4.jpg"},{"title":"[DAY1] 사쿠라자카46 “3rd YEAR ANNIVERSARY LIVE” Re-Streaming (Beyond LIVE ─ TOP)","contents":"2023. 12. 14. 20:00 (KST)","link":"https://beyondlive.com/contents/317","retrieved":1700914834944,"image":"https://static.beyondlive.com/contents/Iy8jcN9hSqgx66iukmw9X04Rw4LKqaGM.jpg"},{"title":"[DAY2] 사쿠라자카46 “3rd YEAR ANNIVERSARY LIVE” Re-Streaming (Beyond LIVE ─ TOP)","contents":"2023. 12. 15. 20:00 (KST)","link":"https://beyondlive.com/contents/319","retrieved":1700997013560,"image":"https://static.beyondlive.com/contents/Er6gAN30P9NZj5iIsO15IBNe6HlT3zgu.jpg"},{"title":"Ado Japan Tour 2023 \"MARS\" (Beyond LIVE ─ Beyond NEXT)","contents":"","link":"https://beyondlive.com/contents/vod/312","retrieved":1701058511701,"image":"https://static.beyondlive.com/vod/GoznXltrzt4CedOyQqIDDn9WK5kVd6bJ.jpg"},{"title":"Eve Arena Tour 2023 「kororon」 Archive (Beyond LIVE ─ Beyond NEXT)","contents":"","link":"https://beyondlive.com/contents/vod/302","retrieved":1701058517599,"image":"https://static.beyondlive.com/contents/d7dc122d8bff4e7c830290dbae2c8d7a.jpg"},{"title":"MMA2023 (멜론 뮤직 어워즈) (Beyond LIVE ─ Beyond NEXT)","contents":"2023. 12. 02. 16:00 (KST)","link":"https://beyondlive.com/contents/320","retrieved":1701058511695,"image":"https://static.beyondlive.com/contents/jf34KtPKnWlMGtw5u982Nrq6rWioxaQg.jpg"},{"title":"2023 aespa FAN MEETING ＜MY DRAMA＞ Re-Streaming (Beyond LIVE ─ Beyond NEXT)","contents":"2023. 12. 02. 20:00 (KST)","link":"https://beyondlive.com/contents/308","retrieved":1700230281465,"image":"https://static.beyondlive.com/contents/c29ccd292dec49b9995ee891d6602dbb.png"},{"title":"THE BOYZ 2ND WORLD TOUR : ZENERATION - ENCORE (Beyond LIVE ─ Beyond NEXT)","contents":"2023. 12. 03. 16:00 (KST)","link":"https://beyondlive.com/contents/315","retrieved":1699499519037,"image":"https://static.beyondlive.com/contents/tJk1kLoSHAjYXnHwYUu0G3yBFEgI9irN.jpg"},{"title":"NCT 127 3RD TOUR ‘NEO CITY : SEOUL - THE UNITY’ Re-Streaming (Beyond LIVE ─ Beyond NEXT)","contents":"2023. 12. 09. 18:00 (KST)","link":"https://beyondlive.com/contents/314","retrieved":1700997013556,"image":"https://static.beyondlive.com/contents/hvKOXHl419ixMNE19JlIDc7SFvoHoK7Q.jpg"},{"title":"[DAY1] 사쿠라자카46 “3rd YEAR ANNIVERSARY LIVE” Re-Streaming (Beyond LIVE ─ Beyond NEXT)","contents":"2023. 12. 14. 20:00 (KST)","link":"https://beyondlive.com/contents/317","retrieved":1700914834944,"image":"https://static.beyondlive.com/contents/05qePApiopIcUufe1FhVKA2qiOSZLhKJ.jpg"},{"title":"[DAY2] 사쿠라자카46 “3rd YEAR ANNIVERSARY LIVE” Re-Streaming (Beyond LIVE ─ Beyond NEXT)","contents":"2023. 12. 15. 20:00 (KST)","link":"https://beyondlive.com/contents/319","retrieved":1700997013560,"image":"https://static.beyondlive.com/contents/RlpqpTqsDrGjjxkxQR1ZXqzdGwFpXrbK.jpg"},{"title":"[12/16] TAEMIN SOLO CONCERT : METAMORPH (Beyond LIVE ─ Beyond NEXT)","contents":"2023. 12. 16. 17:00 (KST)","link":"https://beyondlive.com/contents/321","retrieved":1701054773464,"image":"https://static.beyondlive.com/contents/NomtpbD7TnRrcfikha8P6oPi6NeAR4zD.jpg"},{"title":"[12/17] TAEMIN SOLO CONCERT : METAMORPH (Beyond LIVE ─ Beyond NEXT)","contents":"2023. 12. 17. 16:00 (KST)","link":"https://beyondlive.com/contents/323","retrieved":1701054773468,"image":"https://static.beyondlive.com/contents/hCrKsQCGWrrLiaI7g17rdHuXTZ7AFa8K.jpg"}]}